Metadata-Version: 2.1
Name: lced_connectors
Version: 0.0.2
Summary: lced_connectors
Home-page: 
Author: linwanlong
Author-email: linwanlong88@gmail.com
Classifier: Programming Language :: Python :: 3
Classifier: License :: OSI Approved :: MIT License
Classifier: Operating System :: OS Independent
Requires-Python: >=3.10
